klldFNArabic/__init__.py
klldFNArabic-1.0.1.dist-info/METADATA
klldFNArabic-1.0.1.dist-info/WHEEL
klldFNArabic-1.0.1.dist-info/top_level.txt
klldFNArabic-1.0.1.dist-info/RECORD
